spatialtis_core-0.2.3.dist-info/METADATA
spatialtis_core-0.2.3.dist-info/WHEEL
spatialtis_core/cell_interaction.pyi
spatialtis_core/spatial_analysis.py
spatialtis_core/io.py
spatialtis_core/geo_analysis.py
spatialtis_core/utils.py
spatialtis_core/neighbors.py
spatialtis_core/types.py
spatialtis_core/shape_ops.py
spatialtis_core/__init__.py
spatialtis_core/spatial_de/som_de.py
spatialtis_core/spatial_de/somde/__init__.py
spatialtis_core/spatial_de/somde/som.py
spatialtis_core/spatial_de/somde/util.py
spatialtis_core/spatial_de/__init__.py
spatialtis_core/cell_interaction.py
spatialtis_core/spatialtis_core.cpython-39-x86_64-linux-gnu.so
spatialtis_core-0.2.3.dist-info/RECORD
