Metadata-Version: 2.1
Name: spatialtis_core
Version: 0.2.3
Classifier: Intended Audience :: Science/Research
Classifier: Topic :: Scientific/Engineering :: Bio-Informatics
Classifier: License :: OSI Approved :: MIT License
Classifier: Operating System :: MacOS
Classifier: Operating System :: Microsoft :: Windows
Classifier: Operating System :: POSIX :: Linux
Classifier: Programming Language :: Python :: 3
Classifier: Programming Language :: Python :: 3.7
Classifier: Programming Language :: Python :: 3.8
Classifier: Programming Language :: Python :: 3.9
Classifier: Programming Language :: Python :: 3.10
Classifier: Programming Language :: Python
Classifier: Programming Language :: Rust
Requires-Dist: numpy
Requires-Dist: pandas
Requires-Dist: scipy
Author: Milk <zym.zym1220@gmail.com>
Author-email: Milk <zym.zym1220@gmail.com>
